[
  {
    "id": "1729146445653",
    "title": "Sapphire",
    "description": "Really beautiful gem. I want it",
    "expense": 700
  },
  {
    "id": "1729146522336",
    "title": "Diamonds",
    "description": "Really beautiful gem. I want it",
    "expense": 6887
  },
  {
    "id": "1729146884823",
    "title": "Ruby",
    "description": "Really beautiful gem. I want it",
    "expense": 6426
  },
  {
    "id": "1729146901493",
    "title": "Emerald",
    "description": "тлищг",
    "expense": 927
  },
  {
    "id": "1729147054520",
    "title": "Opal",
    "description": "Really beautiful gem. I want it",
    "expense": 687
  }
]